jax_quant_finance/__init__.py
jax_quant_finance/black_scholes/__init__.py
jax_quant_finance/black_scholes/vanilla_prices.py
jax_quant_finance/black_scholes/vanilla_prices_test.py
jax_quant_finance/experimental/__init__.py
jax_quant_finance/experimental/utils/__init__.py
jax_quant_finance/math/__init__.py
jax_quant_finance/math/diff_ops.py
jax_quant_finance/math/diff_ops_test.py
jax_quant_finance/math/random_sampler.py
jax_quant_finance/math/integration/__init__.py
jax_quant_finance/math/integration/integrate.py
jax_quant_finance/math/integration/integrate_test.py
jax_quant_finance/math/integration/simpson.py
jax_quant_finance/math/integration/simpson_test.py
jax_quant_finance/models/__init__.py
jax_quant_finance/models/euler_sampling.py
jax_quant_finance/models/generic_ito_process.py
jax_quant_finance/models/ito_process.py
jax_quant_finance/models/utils.py
jax_quant_finance/models/utils_test.py
jax_quant_finance/rates/__init__.py
jax_quant_finance/rates/analytics/__init__.py
jax_quant_finance/rates/analytics/cashflows.py
jax_quant_finance/rates/analytics/cashflows_test.py
jax_quant_finance/rates/analytics/swap.py
jax_quant_finance/rates/analytics/swap_test.py
jax_quant_finance/utils/__init__.py
jax_quant_finance/utils/ops.py
jax_quant_finance/utils/ops_test.py
jax_quant_finance/utils/shape_utils.py
jax_quant_finance/utils/shape_utils_test.py
jax_quant_finance-0.0.1.dist-info/LICENSE
jax_quant_finance-0.0.1.dist-info/METADATA
jax_quant_finance-0.0.1.dist-info/WHEEL
jax_quant_finance-0.0.1.dist-info/top_level.txt
jax_quant_finance-0.0.1.dist-info/RECORD
