Metadata-Version: 2.1
Name: jax-quant-finance
Version: 0.0.1
Summary: High Performance Quantative Finance Library on JAX
Home-page: https://github.com/luweizheng/jax-quant-finance
Author: luweizheng
Author-email: luweizheng36@hotmail.com
License: GPLv3
Platform: UNKNOWN
Requires-Python: >=3
Requires-Dist: numpy
Requires-Dist: jax (>=0.3.4)
Requires-Dist: jaxlib (>=0.3.2)
Provides-Extra: complete
Requires-Dist: numpy ; extra == 'complete'
Requires-Dist: jax (>=0.3.4) ; extra == 'complete'
Requires-Dist: jaxlib (>=0.3.2) ; extra == 'complete'
Requires-Dist: pytest ; extra == 'complete'
Provides-Extra: tests
Requires-Dist: pytest ; extra == 'tests'
